ezyara-0.4.1.dist-info/METADATA
ezyara-0.4.1.dist-info/WHEEL
ezyara/__init__.py
ezyara/ezyara.abi3.so
ezyara-0.4.1.dist-info/RECORD
