Metadata-Version: 2.3
Name: ezyara
Version: 0.4.1
Classifier: Programming Language :: Rust
Classifier: Programming Language :: Python :: Implementation :: CPython
Classifier: Programming Language :: Python :: Implementation :: PyPy
Classifier: License :: OSI Approved :: BSD License
Summary: Python bindings for YARA-X
Keywords: pattern-matching,cybersecurity,forensics,malware,yara
Requires-Python: >=3.8
Project-URL: homepage, https://virustotal.github.io/yara-x
Project-URL: repository, https://github.com/VirusTotal/yara-x.git
